{
  "info": {
    "_postman_id": "2e2dddd6-0629-42ac-b736-c002a6beec8d",
    "name": "NetbankAppSpring",
    "schema": "https://schema.getpostman.com/json/collection/v2.1.0/collection.json",
    "_exporter_id": "32777479"
  },
  "item": [
    {
      "name": "auth",
      "item": [
        {
          "name": "login",
          "request": {
            "method": "POST",
            "header": [],
            "body": {
              "mode": "raw",
              "raw": "{\n    \"email\": \"admin@kabastack.dev\",\n    \"password\": \"password123\"\n}",
              "options": {
                "raw": {
                  "language": "json"
                }
              }
            },
            "url": {
              "raw": "{{baseUrl}}api/auth/login",
              "host": [
                "{{baseUrl}}api"
              ],
              "path": [
                "auth",
                "login"
              ]
            }
          },
          "response": []
        }
      ]
    },
    {
      "name": "account",
      "item": [
        {
          "name": "Index Accounts",
          "protocolProfileBehavior": {
            "disableBodyPruning": true
          },
          "request": {
            "auth": {
              "type": "bearer",
              "bearer": [
                {
                  "key": "token",
                  "value": "{{apiToken}}",
                  "type": "string"
                }
              ]
            },
            "method": "GET",
            "header": [],
            "body": {
              "mode": "raw",
              "raw": "",
              "options": {
                "raw": {
                  "language": "json"
                }
              }
            },
            "url": {
              "raw": "{{baseUrl}}api/accounts",
              "host": [
                "{{baseUrl}}api"
              ],
              "path": [
                "accounts"
              ]
            }
          },
          "response": []
        },
        {
          "name": "Get Account details",
          "protocolProfileBehavior": {
            "disableBodyPruning": true
          },
          "request": {
            "auth": {
              "type": "bearer",
              "bearer": [
                {
                  "key": "token",
                  "value": "{{apiToken}}",
                  "type": "string"
                }
              ]
            },
            "method": "GET",
            "header": [],
            "body": {
              "mode": "raw",
              "raw": "",
              "options": {
                "raw": {
                  "language": "json"
                }
              }
            },
            "url": {
              "raw": "{{baseUrl}}api/accounts/ab750cd6-c77c-4210-8a6a-7900481c1c1f",
              "host": [
                "{{baseUrl}}api"
              ],
              "path": [
                "accounts",
                "ab750cd6-c77c-4210-8a6a-7900481c1c1f"
              ]
            }
          },
          "response": []
        }
      ]
    },
    {
      "name": "contact",
      "item": [
        {
          "name": "Index Contacts",
          "protocolProfileBehavior": {
            "disableBodyPruning": true
          },
          "request": {
            "auth": {
              "type": "bearer",
              "bearer": [
                {
                  "key": "token",
                  "value": "{{apiToken}}",
                  "type": "string"
                }
              ]
            },
            "method": "GET",
            "header": [],
            "body": {
              "mode": "raw",
              "raw": "",
              "options": {
                "raw": {
                  "language": "json"
                }
              }
            },
            "url": {
              "raw": "{{baseUrl}}api/contacts",
              "host": [
                "{{baseUrl}}api"
              ],
              "path": [
                "contacts"
              ]
            }
          },
          "response": []
        },
        {
          "name": "Get Contact details",
          "protocolProfileBehavior": {
            "disableBodyPruning": true
          },
          "request": {
            "auth": {
              "type": "bearer",
              "bearer": [
                {
                  "key": "token",
                  "value": "{{apiToken}}",
                  "type": "string"
                }
              ]
            },
            "method": "GET",
            "header": [],
            "body": {
              "mode": "raw",
              "raw": "",
              "options": {
                "raw": {
                  "language": "json"
                }
              }
            },
            "url": {
              "raw": "{{baseUrl}}api/contacts/492dadc8-61f5-42da-a83a-e0ec0411543b",
              "host": [
                "{{baseUrl}}api"
              ],
              "path": [
                "contacts",
                "492dadc8-61f5-42da-a83a-e0ec0411543b"
              ]
            }
          },
          "response": []
        },
        {
          "name": "Create Contact",
          "request": {
            "auth": {
              "type": "bearer",
              "bearer": [
                {
                  "key": "token",
                  "value": "{{apiToken}}",
                  "type": "string"
                }
              ]
            },
            "method": "POST",
            "header": [],
            "body": {
              "mode": "raw",
              "raw": "{\n    \"partnerName\": \"Próba jános\",\n    \"partnerAccountNumber\": \"test\"\n}",
              "options": {
                "raw": {
                  "language": "json"
                }
              }
            },
            "url": {
              "raw": "{{baseUrl}}api/contacts",
              "host": [
                "{{baseUrl}}api"
              ],
              "path": [
                "contacts"
              ]
            }
          },
          "response": []
        },
        {
          "name": "Delete Contact",
          "request": {
            "auth": {
              "type": "bearer",
              "bearer": [
                {
                  "key": "token",
                  "value": "{{apiToken}}",
                  "type": "string"
                }
              ]
            },
            "method": "DELETE",
            "header": [],
            "body": {
              "mode": "raw",
              "raw": "",
              "options": {
                "raw": {
                  "language": "json"
                }
              }
            },
            "url": {
              "raw": "{{baseUrl}}api/contacts/f53456e4-902b-4ef1-9463-d5f15fdedb7a",
              "host": [
                "{{baseUrl}}api"
              ],
              "path": [
                "contacts",
                "f53456e4-902b-4ef1-9463-d5f15fdedb7a"
              ]
            }
          },
          "response": []
        }
      ]
    }
  ],
  "variable": [
    {
      "key": "baseUrl",
      "value": ""
    },
    {
      "key": "apiToken",
      "value": ""
    }
  ]
}